mageflow/__init__.py
mageflow/callbacks.py
mageflow/chain/__init__.py
mageflow/chain/consts.py
mageflow/chain/creator.py
mageflow/chain/messages.py
mageflow/chain/model.py
mageflow/chain/workflows.py
mageflow/cli.py
mageflow/client.py
mageflow/errors.py
mageflow/init.py
mageflow/invokers/__init__.py
mageflow/invokers/base.py
mageflow/invokers/hatchet.py
mageflow/models/__init__.py
mageflow/models/message.py
mageflow/signature/__init__.py
mageflow/signature/consts.py
mageflow/signature/container.py
mageflow/signature/creator.py
mageflow/signature/model.py
mageflow/signature/status.py
mageflow/signature/types.py
mageflow/startup.py
mageflow/swarm/__init__.py
mageflow/swarm/consts.py
mageflow/swarm/creator.py
mageflow/swarm/messages.py
mageflow/swarm/model.py
mageflow/swarm/state.py
mageflow/swarm/workflows.py
mageflow/task/__init__.py
mageflow/task/model.py
mageflow/typing_support.py
mageflow/utils/__init__.py
mageflow/utils/mageflow.py
mageflow/utils/models.py
mageflow/utils/pythonic.py
mageflow/visualizer/__init__.py
mageflow/visualizer/commands.py
mageflow/visualizer/models.py
mageflow/visualizer/server.py
mageflow/visualizer/static/.gitkeep
mageflow/workflows.py
mageflow-0.1.0.dist-info/METADATA
mageflow-0.1.0.dist-info/WHEEL
mageflow-0.1.0.dist-info/entry_points.txt
mageflow-0.1.0.dist-info/licenses/LICENSE
mageflow-0.1.0.dist-info/RECORD
