Metadata-Version: 2.4
Name: mageflow
Version: 0.1.0
Summary: Manage Graph Execution Flow - A unified interface for task orchestration across different task managers
License: MIT
License-File: LICENSE
Keywords: task-orchestration,workflow,task-manager,hatchet,async,redis,task-chain,task-swarm,distributed,microservices,pipeline,graph-execution,workflow-engine,task-queue,python
Author: imaginary-cherry
Author-email: yedidyakfir@gmail.com
Requires-Python: >=3.10,<3.14
Classifier: Development Status :: 3 - Alpha
Classifier: Intended Audience :: Developers
Classifier: License :: OSI Approved :: MIT License
Classifier: Programming Language :: Python :: 3
Classifier: Programming Language :: Python :: 3.10
Classifier: Programming Language :: Python :: 3.11
Classifier: Programming Language :: Python :: 3.12
Classifier: Programming Language :: Python :: 3.13
Classifier: Framework :: AsyncIO
Classifier: Topic :: Software Development :: Libraries :: Python Modules
Classifier: Topic :: System :: Distributed Computing
Classifier: Topic :: Software Development :: Libraries :: Application Frameworks
Classifier: Typing :: Typed
Classifier: Operating System :: OS Independent
Provides-Extra: dev
Provides-Extra: display
Provides-Extra: hatchet
Requires-Dist: click (>=8.0.0,<9.0.0) ; extra == "display"
Requires-Dist: coverage[toml] (>=7.0.0,<8.0.0) ; extra == "dev"
Requires-Dist: dynaconf (>=3.2.12,<4.0.0) ; extra == "dev"
Requires-Dist: fakeredis[json,lua] (>=2.32.1,<3.0.0) ; extra == "dev"
Requires-Dist: fastapi (>=0.109.0,<1.0.0) ; extra == "display"
Requires-Dist: hatchet-sdk (>=1.20.0,<1.22.0) ; extra == "hatchet"
Requires-Dist: httpx (>=0.27.0,<1.0.0) ; extra == "display"
Requires-Dist: psutil (>=7.1.3,<8.0.0) ; extra == "dev"
Requires-Dist: pytest (>=9.0.2,<10.0.0) ; extra == "dev"
Requires-Dist: pytest-asyncio (>=1.2.0,<2.0.0) ; extra == "dev"
Requires-Dist: rapyer (>=1.2.0,<1.3.0)
Requires-Dist: requests (>=2.32.5,<3.0.0) ; extra == "dev"
Requires-Dist: uvicorn[standard] (>=0.27.0,<1.0.0) ; extra == "display"
Project-URL: Bug Tracker, https://github.com/imaginary-cherry/mageflow/issues
Project-URL: Changelog, https://github.com/imaginary-cherry/mageflow/releases
Project-URL: Documentation, https://imaginary-cherry.github.io/mageflow/
Project-URL: Homepage, https://imaginary-cherry.github.io/mageflow/
Project-URL: Repository, https://github.com/imaginary-cherry/mageflow
Project-URL: Source Code, https://github.com/imaginary-cherry/mageflow
